{
 "actions": [],
 "allow_rename": 1,
 "creation": "2025-05-29 08:18:35.873671",
 "doctype": "DocType",
 "editable_grid": 1,
 "engine": "InnoDB",
 "field_order": [
  "log"
 ],
 "fields": [
  {
   "allow_on_submit": 1,
   "fieldname": "log",
   "fieldtype": "Small Text",
   "in_filter": 1,
   "in_global_search": 1,
   "in_list_view": 1,
   "in_preview": 1,
   "in_standard_filter": 1,
   "label": "Log",
   "read_only": 1
  }
 ],
 "grid_page_length": 50,
 "index_web_pages_for_search": 1,
 "istable": 1,
 "links": [],
 "modified": "2025-05-29 08:30:01.864946",
 "modified_by": "Administrator",
 "module": "Delegation Manager",
 "name": "Delegation Log",
 "owner": "Administrator",
 "permissions": [],
 "row_format": "Dynamic",
 "sort_field": "modified",
 "sort_order": "DESC",
 "states": []
}